cause2e/__init__.py
cause2e/_data_type_mgr.py
cause2e/_graph.py
cause2e/_preproc.py
cause2e/_reader.py
cause2e/_regression_mgr.py
cause2e/_result_mgr.py
cause2e/_searcher.py
cause2e/_technical_estimators.py
cause2e/data_generator.py
cause2e/discovery.py
cause2e/estimator.py
cause2e/knowledge.py
cause2e/path_mgr.py
tests/__init__.py
tests/test_data_generator.py
tests/test_data_type_mgr.py
tests/test_discovery.py
tests/test_estimator.py
tests/test_graph.py
tests/test_knowledge.py
tests/test_path_mgr.py
tests/test_preproc.py
tests/test_reader.py
cause2e-0.2.1.dist-info/LICENSE
cause2e-0.2.1.dist-info/METADATA
cause2e-0.2.1.dist-info/WHEEL
cause2e-0.2.1.dist-info/top_level.txt
cause2e-0.2.1.dist-info/RECORD
