Metadata-Version: 2.1
Name: cause2e
Version: 0.2.1
Summary: A package for end-to-end causal analysis
Home-page: https://github.com/MLResearchAtOSRAM/cause2e
Author: Daniel Gruenbaum
Author-email: daniel.gruenbaum@ams-osram.com
License: MIT
Platform: UNKNOWN
Classifier: Programming Language :: Python :: 3.7
Classifier: Programming Language :: Python :: 3.8
Classifier: Programming Language :: Python :: 3.9
Classifier: License :: OSI Approved :: MIT License
Classifier: Operating System :: POSIX :: Linux
Classifier: Operating System :: Microsoft :: Windows
Requires-Python: >=3.7
Requires-Dist: dowhy
Requires-Dist: ipython
Requires-Dist: jinja2
Requires-Dist: pillow
Requires-Dist: pyarrow
Requires-Dist: pycausal
Requires-Dist: seaborn
